MANIFEST.in
README.md
setup.cfg
setup.py
versioneer.py
grabbit/__init__.py
grabbit/_version.py
grabbit/core.py
grabbit/utils.py
grabbit.egg-info/PKG-INFO
grabbit.egg-info/SOURCES.txt
grabbit.egg-info/dependency_links.txt
grabbit.egg-info/top_level.txt
grabbit/extensions/__init__.py
grabbit/extensions/hdfs.py
grabbit/extensions/writable.py
grabbit/external/__init__.py
grabbit/external/inflect.py
grabbit/external/six.py
grabbit/tests/__init__.py
grabbit/tests/test_core.py
grabbit/tests/test_writable.py