Metadata-Version: 1.2
Name: grabbit
Version: 0.2.6
Summary: get grabby with file trees
Home-page: http://github.com/grabbles/grabbit
Maintainer: Tal Yarkoni
Maintainer-email: tyarkoni@gmail.com
License: MIT
Download-URL: http://github.com/grabbles/grabbit/archive/0.2.6.tar.gz
Platform: UNKNOWN
Classifier: License :: OSI Approved :: MIT License
Classifier: Programming Language :: Python :: 2
Classifier: Programming Language :: Python :: 2.7
Classifier: Programming Language :: Python :: 3
Classifier: Programming Language :: Python :: 3.3
Classifier: Programming Language :: Python :: 3.4
